blockdiagrams/DiagramBuilder.py
blockdiagrams/__init__.py
blockdiagrams-1.4.1.dist-info/licenses/LICENSE
blockdiagrams-1.4.1.dist-info/METADATA
blockdiagrams-1.4.1.dist-info/WHEEL
blockdiagrams-1.4.1.dist-info/top_level.txt
blockdiagrams-1.4.1.dist-info/RECORD
