Metadata-Version: 2.4
Name: BlockDiagrams
Version: 1.4.1
Summary: Lightweight library for drawing signal processing block diagrams with any orientation and several branches using Matplotlib
Home-page: https://github.com/miguelmartfern/BlockDiagrams
Author: Miguel Á. Martín-Fernández
Author-email: migmar@uva.es
Classifier: Programming Language :: Python :: 3
Classifier: License :: OSI Approved :: MIT License
Classifier: Operating System :: OS Independent
Requires-Python: >=3.6
License-File: LICENSE
Requires-Dist: matplotlib>=3.0.0
Requires-Dist: numpy>=1.0.0
Dynamic: author
Dynamic: author-email
Dynamic: classifier
Dynamic: description
Dynamic: description-content-type
Dynamic: home-page
Dynamic: license-file
Dynamic: requires-dist
Dynamic: requires-python
Dynamic: summary
